package jogamp.newt.driver.linux;

import com.jogamp.common.util.InterruptSource.Thread;
import com.jogamp.newt.Window;
import com.jogamp.newt.event.KeyEvent;
import com.jogamp.newt.event.WindowEvent;
import com.jogamp.newt.event.WindowListener;
import com.jogamp.newt.event.WindowUpdateEvent;
import java.io.File;
import java.io.PrintStream;
import jogamp.newt.WindowImpl;
import jogamp.newt.driver.KeyTracker;


















































public class LinuxEventDeviceTracker
  implements WindowListener, KeyTracker
{
  private static final LinuxEventDeviceTracker ledt = new LinuxEventDeviceTracker();
  static { InterruptSource.Thread localThread = new InterruptSource.Thread(null, ledteventDeviceManager, "NEWT-LinuxEventDeviceManager");
    localThread.setDaemon(true);
    localThread.start();
  }
  
  public static LinuxEventDeviceTracker getSingleton() {
    return ledt;
  }
  
  private WindowImpl focusedWindow = null;
  private final EventDeviceManager eventDeviceManager = new EventDeviceManager();
  











  private final EventDevicePoller[] eventDevicePollers = new EventDevicePoller[32];
  






  public void windowDestroyNotify(WindowEvent paramWindowEvent)
  {
    Object localObject = paramWindowEvent.getSource();
    if (focusedWindow == localObject) {
      focusedWindow = null;
    }
  }
  



  public void windowGainedFocus(WindowEvent paramWindowEvent)
  {
    Object localObject = paramWindowEvent.getSource();
    if ((localObject instanceof WindowImpl)) {
      focusedWindow = ((WindowImpl)localObject);
    }
  }
  
  public void windowLostFocus(WindowEvent paramWindowEvent)
  {
    Object localObject = paramWindowEvent.getSource();
    if (focusedWindow == localObject) {
      focusedWindow = null;
    }
  }
  
  public static void main(String[] paramArrayOfString) {
    System.setProperty("newt.debug.Window.KeyEvent", "true");
    getSingleton();
    try {
      for (;;) {
        Thread.sleep(1000L);
      }
    }
    catch (InterruptedException localInterruptedException) {
      localInterruptedException.printStackTrace();
    }
  }
  
  public LinuxEventDeviceTracker() {}
  
  public void windowResized(WindowEvent paramWindowEvent) {}
  
  class EventDeviceManager implements Runnable {
    private volatile boolean stop = false;
    
    EventDeviceManager() {}
    
    public void run() { File localFile = new File("/dev/input/");
      
      while (!stop) {
        for (String str1 : localFile.list()) {
          if (str1.startsWith("event")) {
            String str2 = str1.substring(5);
            int i = Integer.parseInt(str2);
            if ((i < 32) && (i >= 0)) {
              if (eventDevicePollers[i] == null) {
                eventDevicePollers[i] = new LinuxEventDeviceTracker.EventDevicePoller(LinuxEventDeviceTracker.this, i);
                InterruptSource.Thread localThread = new InterruptSource.Thread(null, eventDevicePollers[i], "NEWT-LinuxEventDeviceTracker-event" + i);
                localThread.setDaemon(true);
                localThread.start();
              } else if (access$000stop) {
                eventDevicePollers[i] = null;
              }
            }
          }
        }
        try {
          Thread.sleep(2000L);
        }
        catch (InterruptedException localInterruptedException) {
          localInterruptedException.printStackTrace(); } } } }
  
  public void windowMoved(WindowEvent paramWindowEvent) {}
  
  public void windowDestroyed(WindowEvent paramWindowEvent) {}
  
  public void windowRepaint(WindowUpdateEvent paramWindowUpdateEvent) {}
  
  class EventDevicePoller implements Runnable { private volatile boolean stop = false;
    private final String eventDeviceName;
    
    public EventDevicePoller(int paramInt) {
      eventDeviceName = ("/dev/input/event" + paramInt);
    }
    
    /* Error */
    public void run()
    {
      // Byte code:
      //   0: bipush 16
      //   2: newarray byte
      //   4: astore_1
      //   5: aload_1
      //   6: invokestatic 11	java/nio/ByteBuffer:wrap	([B)Ljava/nio/ByteBuffer;
      //   9: astore_2
      //   10: new 12	com/jogamp/common/nio/StructAccessor
      //   13: dup
      //   14: aload_2
      //   15: invokespecial 13	com/jogamp/common/nio/StructAccessor:<init>	(Ljava/nio/ByteBuffer;)V
      //   18: astore_3
      //   19: new 14	java/io/File
      //   22: dup
      //   23: aload_0
      //   24: getfield 10	jogamp/newt/driver/linux/LinuxEventDeviceTracker$EventDevicePoller:eventDeviceName	Ljava/lang/String;
      //   27: invokespecial 15	java/io/File:<init>	(Ljava/lang/String;)V
      //   30: astore 4
      //   32: aload 4
      //   34: invokevirtual 16	java/io/File:setReadOnly	()Z
      //   37: pop
      //   38: new 17	java/io/FileInputStream
      //   41: dup
      //   42: aload 4
      //   44: invokespecial 18	java/io/FileInputStream:<init>	(Ljava/io/File;)V
      //   47: astore 5
      //   49: goto +11 -> 60
      //   52: astore 6
      //   54: aload_0
      //   55: iconst_1
      //   56: putfield 1	jogamp/newt/driver/linux/LinuxEventDeviceTracker$EventDevicePoller:stop	Z
      //   59: return
      //   60: iconst_0
      //   61: istore 11
      //   63: bipush 32
      //   65: istore 12
      //   67: iconst_0
      //   68: istore 13
      //   70: iconst_0
      //   71: istore 14
      //   73: aload_0
      //   74: getfield 1	jogamp/newt/driver/linux/LinuxEventDeviceTracker$EventDevicePoller:stop	Z
      //   77: ifne +930 -> 1007
      //   80: bipush 16
      //   82: istore 15
      //   84: iload 15
      //   86: ifle +53 -> 139
      //   89: iconst_0
      //   90: istore 16
      //   92: aload 5
      //   94: aload_1
      //   95: iconst_0
      //   96: iload 15
      //   98: invokevirtual 21	java/io/InputStream:read	([BII)I
      //   101: istore 16
      //   103: goto +13 -> 116
      //   106: astore 17
      //   108: aload_0
      //   109: iconst_1
      //   110: putfield 1	jogamp/newt/driver/linux/LinuxEventDeviceTracker$EventDevicePoller:stop	Z
      //   113: goto +894 -> 1007
      //   116: iload 16
      //   118: ifge +11 -> 129
      //   121: aload_0
      //   122: iconst_1
      //   123: putfield 1	jogamp/newt/driver/linux/LinuxEventDeviceTracker$EventDevicePoller:stop	Z
      //   126: goto +881 -> 1007
      //   129: iload 15
      //   131: iload 16
      //   133: isub
      //   134: istore 15
      //   136: goto -52 -> 84
      //   139: aload_3
      //   140: iconst_0
      //   141: invokevirtual 23	com/jogamp/common/nio/StructAccessor:getIntAt	(I)I
      //   144: istore 6
      //   146: aload_3
      //   147: iconst_4
      //   148: invokevirtual 24	com/jogamp/common/nio/StructAccessor:getShortAt	(I)S
      //   151: istore 7
      //   153: aload_3
      //   154: bipush 8
      //   156: invokevirtual 24	com/jogamp/common/nio/StructAccessor:getShortAt	(I)S
      //   159: istore 8
      //   161: aload_3
      //   162: bipush 10
      //   164: invokevirtual 24	com/jogamp/common/nio/StructAccessor:getShortAt	(I)S
      //   167: istore 9
      //   169: aload_3
      //   170: bipush 12
      //   172: invokevirtual 23	com/jogamp/common/nio/StructAccessor:getIntAt	(I)I
      //   175: istore 10
      //   177: iload 8
      //   179: tableswitch	default:+753->932, 0:+33->212, 1:+59->238, 2:+753->932, 3:+753->932, 4:+744->923
      //   212: iconst_0
      //   213: istore 13
      //   215: iconst_0
      //   216: istore 11
      //   218: iconst_0
      //   219: istore 12
      //   221: getstatic 25	com/jogamp/newt/Window:DEBUG_KEY_EVENT	Z
      //   224: ifeq +780 -> 1004
      //   227: getstatic 26	java/lang/System:out	Ljava/io/PrintStream;
      //   230: ldc 27
      //   232: invokevirtual 28	java/io/PrintStream:println	(Ljava/lang/String;)V
      //   235: goto +769 -> 1004
      //   238: aload_0
      //   239: iload 9
      //   241: invokespecial 29	jogamp/newt/driver/linux/LinuxEventDeviceTracker$EventDevicePoller:LinuxEVKey2NewtVKey	(S)S
      //   244: istore 11
      //   246: aload_0
      //   247: iload 11
      //   249: iload 14
      //   251: invokespecial 30	jogamp/newt/driver/linux/LinuxEventDeviceTracker$EventDevicePoller:NewtVKey2Unicode	(SI)C
      //   254: istore 12
      //   256: getstatic 25	com/jogamp/newt/Window:DEBUG_KEY_EVENT	Z
      //   259: ifeq +69 -> 328
      //   262: getstatic 26	java/lang/System:out	Ljava/io/PrintStream;
      //   265: new 4	java/lang/StringBuilder
      //   268: dup
      //   269: invokespecial 5	java/lang/StringBuilder:<init>	()V
      //   272: ldc 31
      //   274: invokevirtual 7	java/lang/StringBuilder:append	(Ljava/lang/String;)Ljava/lang/StringBuilder;
      //   277: iload 6
      //   279: invokevirtual 8	java/lang/StringBuilder:append	(I)Ljava/lang/StringBuilder;
      //   282: ldc 32
      //   284: invokevirtual 7	java/lang/StringBuilder:append	(Ljava/lang/String;)Ljava/lang/StringBuilder;
      //   287: iload 7
      //   289: invokevirtual 8	java/lang/StringBuilder:append	(I)Ljava/lang/StringBuilder;
      //   292: ldc 33
      //   294: invokevirtual 7	java/lang/StringBuilder:append	(Ljava/lang/String;)Ljava/lang/StringBuilder;
      //   297: iload 8
      //   299: invokevirtual 8	java/lang/StringBuilder:append	(I)Ljava/lang/StringBuilder;
      //   302: ldc 34
      //   304: invokevirtual 7	java/lang/StringBuilder:append	(Ljava/lang/String;)Ljava/lang/StringBuilder;
      //   307: iload 9
      //   309: invokevirtual 8	java/lang/StringBuilder:append	(I)Ljava/lang/StringBuilder;
      //   312: ldc 35
      //   314: invokevirtual 7	java/lang/StringBuilder:append	(Ljava/lang/String;)Ljava/lang/StringBuilder;
      //   317: iload 10
      //   319: invokevirtual 8	java/lang/StringBuilder:append	(I)Ljava/lang/StringBuilder;
      //   322: invokevirtual 9	java/lang/StringBuilder:toString	()Ljava/lang/String;
      //   325: invokevirtual 28	java/io/PrintStream:println	(Ljava/lang/String;)V
      //   328: iload 10
      //   330: tableswitch	default:+590->920, 0:+26->356, 1:+189->519, 2:+351->681
      //   356: sipush 301
      //   359: istore 13
      //   361: iload 11
      //   363: tableswitch	default:+70->433, 15:+33->396, 16:+70->433, 17:+63->426, 18:+43->406, 19:+53->416
      //   396: iload 14
      //   398: bipush -2
      //   400: iand
      //   401: istore 14
      //   403: goto +30 -> 433
      //   406: iload 14
      //   408: bipush -9
      //   410: iand
      //   411: istore 14
      //   413: goto +20 -> 433
      //   416: iload 14
      //   418: bipush -17
      //   420: iand
      //   421: istore 14
      //   423: goto +10 -> 433
      //   426: iload 14
      //   428: bipush -3
      //   430: iand
      //   431: istore 14
      //   433: aconst_null
      //   434: aload_0
      //   435: getfield 2	jogamp/newt/driver/linux/LinuxEventDeviceTracker$EventDevicePoller:this$0	Ljogamp/newt/driver/linux/LinuxEventDeviceTracker;
      //   438: invokestatic 37	jogamp/newt/driver/linux/LinuxEventDeviceTracker:access$200	(Ljogamp/newt/driver/linux/LinuxEventDeviceTracker;)Ljogamp/newt/WindowImpl;
      //   441: if_acmpeq +23 -> 464
      //   444: aload_0
      //   445: getfield 2	jogamp/newt/driver/linux/LinuxEventDeviceTracker$EventDevicePoller:this$0	Ljogamp/newt/driver/linux/LinuxEventDeviceTracker;
      //   448: invokestatic 37	jogamp/newt/driver/linux/LinuxEventDeviceTracker:access$200	(Ljogamp/newt/driver/linux/LinuxEventDeviceTracker;)Ljogamp/newt/WindowImpl;
      //   451: iload 13
      //   453: iload 14
      //   455: iload 11
      //   457: iload 11
      //   459: iload 12
      //   461: invokevirtual 38	jogamp/newt/WindowImpl:sendKeyEvent	(SISSC)V
      //   464: getstatic 25	com/jogamp/newt/Window:DEBUG_KEY_EVENT	Z
      //   467: ifeq +453 -> 920
      //   470: getstatic 26	java/lang/System:out	Ljava/io/PrintStream;
      //   473: new 4	java/lang/StringBuilder
      //   476: dup
      //   477: invokespecial 5	java/lang/StringBuilder:<init>	()V
      //   480: ldc 39
      //   482: invokevirtual 7	java/lang/StringBuilder:append	(Ljava/lang/String;)Ljava/lang/StringBuilder;
      //   485: iload 11
      //   487: invokevirtual 8	java/lang/StringBuilder:append	(I)Ljava/lang/StringBuilder;
      //   490: ldc 40
      //   492: invokevirtual 7	java/lang/StringBuilder:append	(Ljava/lang/String;)Ljava/lang/StringBuilder;
      //   495: iload 12
      //   497: invokevirtual 41	java/lang/StringBuilder:append	(C)Ljava/lang/StringBuilder;
      //   500: ldc 42
      //   502: invokevirtual 7	java/lang/StringBuilder:append	(Ljava/lang/String;)Ljava/lang/StringBuilder;
      //   505: iload 14
      //   507: invokevirtual 8	java/lang/StringBuilder:append	(I)Ljava/lang/StringBuilder;
      //   510: invokevirtual 9	java/lang/StringBuilder:toString	()Ljava/lang/String;
      //   513: invokevirtual 28	java/io/PrintStream:println	(Ljava/lang/String;)V
      //   516: goto +404 -> 920
      //   519: sipush 300
      //   522: istore 13
      //   524: iload 11
      //   526: tableswitch	default:+69->595, 15:+34->560, 16:+69->595, 17:+63->589, 18:+43->569, 19:+53->579
      //   560: iload 14
      //   562: iconst_1
      //   563: ior
      //   564: istore 14
      //   566: goto +29 -> 595
      //   569: iload 14
      //   571: bipush 8
      //   573: ior
      //   574: istore 14
      //   576: goto +19 -> 595
      //   579: iload 14
      //   581: bipush 16
      //   583: ior
      //   584: istore 14
      //   586: goto +9 -> 595
      //   589: iload 14
      //   591: iconst_2
      //   592: ior
      //   593: istore 14
      //   595: aconst_null
      //   596: aload_0
      //   597: getfield 2	jogamp/newt/driver/linux/LinuxEventDeviceTracker$EventDevicePoller:this$0	Ljogamp/newt/driver/linux/LinuxEventDeviceTracker;
      //   600: invokestatic 37	jogamp/newt/driver/linux/LinuxEventDeviceTracker:access$200	(Ljogamp/newt/driver/linux/LinuxEventDeviceTracker;)Ljogamp/newt/WindowImpl;
      //   603: if_acmpeq +23 -> 626
      //   606: aload_0
      //   607: getfield 2	jogamp/newt/driver/linux/LinuxEventDeviceTracker$EventDevicePoller:this$0	Ljogamp/newt/driver/linux/LinuxEventDeviceTracker;
      //   610: invokestatic 37	jogamp/newt/driver/linux/LinuxEventDeviceTracker:access$200	(Ljogamp/newt/driver/linux/LinuxEventDeviceTracker;)Ljogamp/newt/WindowImpl;
      //   613: iload 13
      //   615: iload 14
      //   617: iload 11
      //   619: iload 11
      //   621: iload 12
      //   623: invokevirtual 38	jogamp/newt/WindowImpl:sendKeyEvent	(SISSC)V
      //   626: getstatic 25	com/jogamp/newt/Window:DEBUG_KEY_EVENT	Z
      //   629: ifeq +291 -> 920
      //   632: getstatic 26	java/lang/System:out	Ljava/io/PrintStream;
      //   635: new 4	java/lang/StringBuilder
      //   638: dup
      //   639: invokespecial 5	java/lang/StringBuilder:<init>	()V
      //   642: ldc 43
      //   644: invokevirtual 7	java/lang/StringBuilder:append	(Ljava/lang/String;)Ljava/lang/StringBuilder;
      //   647: iload 11
      //   649: invokevirtual 8	java/lang/StringBuilder:append	(I)Ljava/lang/StringBuilder;
      //   652: ldc 40
      //   654: invokevirtual 7	java/lang/StringBuilder:append	(Ljava/lang/String;)Ljava/lang/StringBuilder;
      //   657: iload 12
      //   659: invokevirtual 41	java/lang/StringBuilder:append	(C)Ljava/lang/StringBuilder;
      //   662: ldc 42
      //   664: invokevirtual 7	java/lang/StringBuilder:append	(Ljava/lang/String;)Ljava/lang/StringBuilder;
      //   667: iload 14
      //   669: invokevirtual 8	java/lang/StringBuilder:append	(I)Ljava/lang/StringBuilder;
      //   672: invokevirtual 9	java/lang/StringBuilder:toString	()Ljava/lang/String;
      //   675: invokevirtual 28	java/io/PrintStream:println	(Ljava/lang/String;)V
      //   678: goto +242 -> 920
      //   681: sipush 300
      //   684: istore 13
      //   686: iload 14
      //   688: ldc 44
      //   690: ior
      //   691: istore 14
      //   693: iload 11
      //   695: tableswitch	default:+68->763, 15:+33->728, 16:+68->763, 17:+62->757, 18:+42->737, 19:+52->747
      //   728: iload 14
      //   730: iconst_1
      //   731: ior
      //   732: istore 14
      //   734: goto +29 -> 763
      //   737: iload 14
      //   739: bipush 8
      //   741: ior
      //   742: istore 14
      //   744: goto +19 -> 763
      //   747: iload 14
      //   749: bipush 16
      //   751: ior
      //   752: istore 14
      //   754: goto +9 -> 763
      //   757: iload 14
      //   759: iconst_2
      //   760: ior
      //   761: istore 14
      //   763: aconst_null
      //   764: aload_0
      //   765: getfield 2	jogamp/newt/driver/linux/LinuxEventDeviceTracker$EventDevicePoller:this$0	Ljogamp/newt/driver/linux/LinuxEventDeviceTracker;
      //   768: invokestatic 37	jogamp/newt/driver/linux/LinuxEventDeviceTracker:access$200	(Ljogamp/newt/driver/linux/LinuxEventDeviceTracker;)Ljogamp/newt/WindowImpl;
      //   771: if_acmpeq +44 -> 815
      //   774: aload_0
      //   775: getfield 2	jogamp/newt/driver/linux/LinuxEventDeviceTracker$EventDevicePoller:this$0	Ljogamp/newt/driver/linux/LinuxEventDeviceTracker;
      //   778: invokestatic 37	jogamp/newt/driver/linux/LinuxEventDeviceTracker:access$200	(Ljogamp/newt/driver/linux/LinuxEventDeviceTracker;)Ljogamp/newt/WindowImpl;
      //   781: sipush 301
      //   784: iload 14
      //   786: iload 11
      //   788: iload 11
      //   790: iload 12
      //   792: invokevirtual 38	jogamp/newt/WindowImpl:sendKeyEvent	(SISSC)V
      //   795: aload_0
      //   796: getfield 2	jogamp/newt/driver/linux/LinuxEventDeviceTracker$EventDevicePoller:this$0	Ljogamp/newt/driver/linux/LinuxEventDeviceTracker;
      //   799: invokestatic 37	jogamp/newt/driver/linux/LinuxEventDeviceTracker:access$200	(Ljogamp/newt/driver/linux/LinuxEventDeviceTracker;)Ljogamp/newt/WindowImpl;
      //   802: iload 13
      //   804: iload 14
      //   806: iload 11
      //   808: iload 11
      //   810: iload 12
      //   812: invokevirtual 38	jogamp/newt/WindowImpl:sendKeyEvent	(SISSC)V
      //   815: getstatic 25	com/jogamp/newt/Window:DEBUG_KEY_EVENT	Z
      //   818: ifeq +95 -> 913
      //   821: getstatic 26	java/lang/System:out	Ljava/io/PrintStream;
      //   824: new 4	java/lang/StringBuilder
      //   827: dup
      //   828: invokespecial 5	java/lang/StringBuilder:<init>	()V
      //   831: ldc 45
      //   833: invokevirtual 7	java/lang/StringBuilder:append	(Ljava/lang/String;)Ljava/lang/StringBuilder;
      //   836: iload 11
      //   838: invokevirtual 8	java/lang/StringBuilder:append	(I)Ljava/lang/StringBuilder;
      //   841: ldc 40
      //   843: invokevirtual 7	java/lang/StringBuilder:append	(Ljava/lang/String;)Ljava/lang/StringBuilder;
      //   846: iload 12
      //   848: invokevirtual 41	java/lang/StringBuilder:append	(C)Ljava/lang/StringBuilder;
      //   851: ldc 42
      //   853: invokevirtual 7	java/lang/StringBuilder:append	(Ljava/lang/String;)Ljava/lang/StringBuilder;
      //   856: iload 14
      //   858: invokevirtual 8	java/lang/StringBuilder:append	(I)Ljava/lang/StringBuilder;
      //   861: invokevirtual 9	java/lang/StringBuilder:toString	()Ljava/lang/String;
      //   864: invokevirtual 28	java/io/PrintStream:println	(Ljava/lang/String;)V
      //   867: getstatic 26	java/lang/System:out	Ljava/io/PrintStream;
      //   870: new 4	java/lang/StringBuilder
      //   873: dup
      //   874: invokespecial 5	java/lang/StringBuilder:<init>	()V
      //   877: ldc 46
      //   879: invokevirtual 7	java/lang/StringBuilder:append	(Ljava/lang/String;)Ljava/lang/StringBuilder;
      //   882: iload 11
      //   884: invokevirtual 8	java/lang/StringBuilder:append	(I)Ljava/lang/StringBuilder;
      //   887: ldc 40
      //   889: invokevirtual 7	java/lang/StringBuilder:append	(Ljava/lang/String;)Ljava/lang/StringBuilder;
      //   892: iload 12
      //   894: invokevirtual 41	java/lang/StringBuilder:append	(C)Ljava/lang/StringBuilder;
      //   897: ldc 42
      //   899: invokevirtual 7	java/lang/StringBuilder:append	(Ljava/lang/String;)Ljava/lang/StringBuilder;
      //   902: iload 14
      //   904: invokevirtual 8	java/lang/StringBuilder:append	(I)Ljava/lang/StringBuilder;
      //   907: invokevirtual 9	java/lang/StringBuilder:toString	()Ljava/lang/String;
      //   910: invokevirtual 28	java/io/PrintStream:println	(Ljava/lang/String;)V
      //   913: iload 14
      //   915: ldc 47
      //   917: iand
      //   918: istore 14
      //   920: goto +84 -> 1004
      //   923: iload 9
      //   925: iconst_4
      //   926: if_icmpne +78 -> 1004
      //   929: goto +75 -> 1004
      //   932: getstatic 25	com/jogamp/newt/Window:DEBUG_KEY_EVENT	Z
      //   935: ifeq +69 -> 1004
      //   938: getstatic 26	java/lang/System:out	Ljava/io/PrintStream;
      //   941: new 4	java/lang/StringBuilder
      //   944: dup
      //   945: invokespecial 5	java/lang/StringBuilder:<init>	()V
      //   948: ldc 48
      //   950: invokevirtual 7	java/lang/StringBuilder:append	(Ljava/lang/String;)Ljava/lang/StringBuilder;
      //   953: iload 6
      //   955: invokevirtual 8	java/lang/StringBuilder:append	(I)Ljava/lang/StringBuilder;
      //   958: ldc 32
      //   960: invokevirtual 7	java/lang/StringBuilder:append	(Ljava/lang/String;)Ljava/lang/StringBuilder;
      //   963: iload 7
      //   965: invokevirtual 8	java/lang/StringBuilder:append	(I)Ljava/lang/StringBuilder;
      //   968: ldc 33
      //   970: invokevirtual 7	java/lang/StringBuilder:append	(Ljava/lang/String;)Ljava/lang/StringBuilder;
      //   973: iload 8
      //   975: invokevirtual 8	java/lang/StringBuilder:append	(I)Ljava/lang/StringBuilder;
      //   978: ldc 34
      //   980: invokevirtual 7	java/lang/StringBuilder:append	(Ljava/lang/String;)Ljava/lang/StringBuilder;
      //   983: iload 9
      //   985: invokevirtual 8	java/lang/StringBuilder:append	(I)Ljava/lang/StringBuilder;
      //   988: ldc 35
      //   990: invokevirtual 7	java/lang/StringBuilder:append	(Ljava/lang/String;)Ljava/lang/StringBuilder;
      //   993: iload 10
      //   995: invokevirtual 8	java/lang/StringBuilder:append	(I)Ljava/lang/StringBuilder;
      //   998: invokevirtual 9	java/lang/StringBuilder:toString	()Ljava/lang/String;
      //   1001: invokevirtual 28	java/io/PrintStream:println	(Ljava/lang/String;)V
      //   1004: goto -931 -> 73
      //   1007: aconst_null
      //   1008: aload 5
      //   1010: if_acmpeq +13 -> 1023
      //   1013: aload 5
      //   1015: invokevirtual 49	java/io/InputStream:close	()V
      //   1018: goto +5 -> 1023
      //   1021: astore 15
      //   1023: aload_0
      //   1024: iconst_1
      //   1025: putfield 1	jogamp/newt/driver/linux/LinuxEventDeviceTracker$EventDevicePoller:stop	Z
      //   1028: return
      // Line number table:
      //   Java source line #187	-> byte code offset #0
      //   Java source line #199	-> byte code offset #5
      //   Java source line #200	-> byte code offset #10
      //   Java source line #201	-> byte code offset #19
      //   Java source line #202	-> byte code offset #32
      //   Java source line #205	-> byte code offset #38
      //   Java source line #209	-> byte code offset #49
      //   Java source line #206	-> byte code offset #52
      //   Java source line #207	-> byte code offset #54
      //   Java source line #208	-> byte code offset #59
      //   Java source line #217	-> byte code offset #60
      //   Java source line #218	-> byte code offset #63
      //   Java source line #219	-> byte code offset #67
      //   Java source line #220	-> byte code offset #70
      //   Java source line #223	-> byte code offset #73
      //   Java source line #224	-> byte code offset #80
      //   Java source line #225	-> byte code offset #84
      //   Java source line #226	-> byte code offset #89
      //   Java source line #228	-> byte code offset #92
      //   Java source line #232	-> byte code offset #103
      //   Java source line #229	-> byte code offset #106
      //   Java source line #230	-> byte code offset #108
      //   Java source line #231	-> byte code offset #113
      //   Java source line #233	-> byte code offset #116
      //   Java source line #234	-> byte code offset #121
      //   Java source line #235	-> byte code offset #126
      //   Java source line #237	-> byte code offset #129
      //   Java source line #239	-> byte code offset #136
      //   Java source line #241	-> byte code offset #139
      //   Java source line #242	-> byte code offset #146
      //   Java source line #243	-> byte code offset #153
      //   Java source line #244	-> byte code offset #161
      //   Java source line #245	-> byte code offset #169
      //   Java source line #255	-> byte code offset #177
      //   Java source line #258	-> byte code offset #212
      //   Java source line #259	-> byte code offset #215
      //   Java source line #260	-> byte code offset #218
      //   Java source line #261	-> byte code offset #221
      //   Java source line #262	-> byte code offset #227
      //   Java source line #266	-> byte code offset #238
      //   Java source line #267	-> byte code offset #246
      //   Java source line #268	-> byte code offset #256
      //   Java source line #269	-> byte code offset #262
      //   Java source line #272	-> byte code offset #328
      //   Java source line #274	-> byte code offset #356
      //   Java source line #276	-> byte code offset #361
      //   Java source line #278	-> byte code offset #396
      //   Java source line #279	-> byte code offset #403
      //   Java source line #281	-> byte code offset #406
      //   Java source line #282	-> byte code offset #413
      //   Java source line #284	-> byte code offset #416
      //   Java source line #285	-> byte code offset #423
      //   Java source line #287	-> byte code offset #426
      //   Java source line #291	-> byte code offset #433
      //   Java source line #292	-> byte code offset #444
      //   Java source line #294	-> byte code offset #464
      //   Java source line #295	-> byte code offset #470
      //   Java source line #299	-> byte code offset #519
      //   Java source line #301	-> byte code offset #524
      //   Java source line #303	-> byte code offset #560
      //   Java source line #304	-> byte code offset #566
      //   Java source line #306	-> byte code offset #569
      //   Java source line #307	-> byte code offset #576
      //   Java source line #309	-> byte code offset #579
      //   Java source line #310	-> byte code offset #586
      //   Java source line #312	-> byte code offset #589
      //   Java source line #316	-> byte code offset #595
      //   Java source line #317	-> byte code offset #606
      //   Java source line #319	-> byte code offset #626
      //   Java source line #320	-> byte code offset #632
      //   Java source line #324	-> byte code offset #681
      //   Java source line #325	-> byte code offset #686
      //   Java source line #327	-> byte code offset #693
      //   Java source line #329	-> byte code offset #728
      //   Java source line #330	-> byte code offset #734
      //   Java source line #332	-> byte code offset #737
      //   Java source line #333	-> byte code offset #744
      //   Java source line #335	-> byte code offset #747
      //   Java source line #336	-> byte code offset #754
      //   Java source line #338	-> byte code offset #757
      //   Java source line #342	-> byte code offset #763
      //   Java source line #344	-> byte code offset #774
      //   Java source line #346	-> byte code offset #795
      //   Java source line #348	-> byte code offset #815
      //   Java source line #349	-> byte code offset #821
      //   Java source line #350	-> byte code offset #867
      //   Java source line #352	-> byte code offset #913
      //   Java source line #355	-> byte code offset #920
      //   Java source line #357	-> byte code offset #923
      //   Java source line #365	-> byte code offset #932
      //   Java source line #366	-> byte code offset #938
      //   Java source line #369	-> byte code offset #1004
      //   Java source line #371	-> byte code offset #1007
      //   Java source line #373	-> byte code offset #1013
      //   Java source line #375	-> byte code offset #1018
      //   Java source line #374	-> byte code offset #1021
      //   Java source line #377	-> byte code offset #1023
      //   Java source line #378	-> byte code offset #1028
      // Local variable table:
      //   start	length	slot	name	signature
      //   0	1029	0	this	EventDevicePoller
      //   4	91	1	arrayOfByte	byte[]
      //   9	6	2	localByteBuffer	java.nio.ByteBuffer
      //   18	152	3	localStructAccessor	com.jogamp.common.nio.StructAccessor
      //   30	13	4	localFile	File
      //   47	967	5	localFileInputStream	java.io.FileInputStream
      //   52	1	6	localFileNotFoundException	java.io.FileNotFoundException
      //   144	810	6	i	int
      //   151	813	7	j	int
      //   159	815	8	k	int
      //   167	817	9	s1	short
      //   175	819	10	m	int
      //   61	822	11	s2	short
      //   65	828	12	c	char
      //   68	735	13	s3	short
      //   71	848	14	n	int
      //   82	53	15	i1	int
      //   1021	1	15	localIOException1	java.io.IOException
      //   90	44	16	i2	int
      //   106	1	17	localIOException2	java.io.IOException
      // Exception table:
      //   from	to	target	type
      //   38	49	52	java/io/FileNotFoundException
      //   92	103	106	java/io/IOException
      //   1013	1018	1021	java/io/IOException
    }
    
    private char NewtVKey2Unicode(short paramShort, int paramInt)
    {
      if (KeyEvent.isPrintableKey(paramShort, true)) {
        if ((paramInt & 0x1) == 1) {
          return (char)paramShort;
        }
        return String.valueOf((char)paramShort).toLowerCase().charAt(0);
      }
      
      return '\000';
    }
    


    private char LinuxEVKey2Unicode(short paramShort)
    {
      switch (paramShort) {
      case 17: 
        return 'w';
      case 31: 
        return 's';
      case 30: 
        return 'a';
      case 32: 
        return 'd';
      case 1: 
        return '\033';
      case 28: 
      case 96: 
        return '\n';
      case 57: 
        return ' ';
      case 11: 
      case 82: 
        return '0';
      case 2: 
      case 79: 
        return '1';
      case 3: 
      case 80: 
        return '2';
      case 4: 
      case 81: 
        return '3';
      case 5: 
      case 75: 
        return '4';
      case 6: 
      case 76: 
        return '5';
      case 7: 
      case 77: 
        return '6';
      case 8: 
      case 71: 
        return '7';
      case 9: 
      case 72: 
        return '8';
      case 10: 
      case 73: 
        return '9';
      }
      
      

      return '\000';
    }
    
    private short LinuxEVKey2NewtVKey(short paramShort)
    {
      switch (paramShort) {
      case 1: 
        return 27;
      case 2: 
        return 49;
      case 79: 
        return 129;
      case 3: 
        return 50;
      case 80: 
        return 130;
      case 4: 
        return 51;
      case 81: 
        return 131;
      case 5: 
        return 52;
      case 75: 
        return 132;
      case 6: 
        return 53;
      case 76: 
        return 133;
      case 7: 
        return 54;
      case 77: 
        return 134;
      case 8: 
        return 55;
      case 71: 
        return 135;
      case 9: 
        return 56;
      case 72: 
        return 136;
      case 10: 
        return 57;
      case 73: 
        return 137;
      case 11: 
        return 48;
      case 82: 
        return 128;
      case 12: 
        return 45;
      case 13: 
        return 61;
      case 14: 
        return 8;
      
      case 15: 
        return 9;
      case 16: 
        return 81;
      case 17: 
        return 87;
      case 18: 
        return 69;
      case 19: 
        return 82;
      case 20: 
        return 84;
      case 21: 
        return 89;
      case 22: 
        return 85;
      case 23: 
        return 73;
      case 24: 
        return 79;
      case 25: 
        return 80;
      case 26: 
        return 40;
      case 27: 
        return 41;
      case 28: 
      case 96: 
        return 13;
      
      case 29: 
        return 17;
      case 30: 
        return 65;
      case 31: 
        return 83;
      case 32: 
        return 68;
      case 33: 
        return 70;
      case 34: 
        return 71;
      case 35: 
        return 72;
      case 36: 
        return 74;
      case 37: 
        return 75;
      case 38: 
        return 76;
      case 39: 
        return 59;
      case 40: 
        return 39;
      case 41: 
        return 96;
      
      case 42: 
        return 15;
      case 43: 
        return 92;
      case 44: 
        return 90;
      case 45: 
        return 88;
      case 46: 
        return 67;
      case 47: 
        return 86;
      case 48: 
        return 66;
      case 49: 
        return 78;
      case 50: 
        return 77;
      case 51: 
        return 44;
      case 52: 
        return 46;
      case 53: 
        return 47;
      case 54: 
        return 15;
      case 55: 
        return 42;
      case 56: 
        return 18;
      case 57: 
        return 32;
      case 58: 
        return 20;
      
      case 59: 
        return 97;
      case 60: 
        return 98;
      case 61: 
        return 99;
      case 62: 
        return 100;
      case 63: 
        return 101;
      case 64: 
        return 102;
      case 65: 
        return 103;
      case 66: 
        return 104;
      case 67: 
        return 105;
      case 68: 
        return 106;
      
      case 69: 
        return 148;
      case 70: 
        return 23;
      
      case 74: 
        return 45;
      case 78: 
        return 43;
      case 83: 
        return 46;
      
      case 85: 
      case 86: 
        break;
      

      case 87: 
        return 107;
      case 88: 
        return 108;
      
      case 89: 
        return 63634;
      case 90: 
        return 63638;
      case 91: 
        return 63639;
      case 92: 
        break;
      case 93: 
        break;
      case 94: 
        break;
      
      case 95: 
        break;
      
      case 97: 
        return 17;
      case 98: 
        return 47;
      
      case 99: 
        break;
      
      case 100: 
        return 18;
      case 101: 
        break;
      case 102: 
        return 2;
      case 103: 
        return 150;
      case 104: 
        return 16;
      case 105: 
        return 149;
      case 106: 
        return 151;
      case 107: 
        return 3;
      case 108: 
        return 152;
      case 109: 
        return 11;
      case 110: 
        return 26;
      case 111: 
        return 147;
      case 112: 
        break;
      case 113: 
        break;
      case 114: 
        break;
      case 115: 
        break;
      
      case 116: 
        break;
      
      case 117: 
        return 61;
      case 118: 
        break;
      case 119: 
        return 22;
      case 120: 
        break;
      case 121: 
        return 44;
      case 122: 
        break;
      case 123: 
        break;
      case 124: 
        break;
      
      case 125: 
      case 126: 
        return 155;
      case 127: 
        return 157;
      
      case 128: 
        return 159;
      case 129: 
        return 63613;
      case 130: 
        return 63615;
      case 131: 
        return 63612;
      case 132: 
        break;
      case 133: 
        return 63610;
      case 134: 
        break;
      case 135: 
        return 63611;
      case 136: 
        return 63614;
      case 137: 
        return 63609;
      case 138: 
        return 156;
      case 139: 
        break;
      case 140: 
        break;
      case 141: 
        break;
      case 142: 
        break;
      case 143: 
        break;
      case 144: 
        break;
      case 145: 
        break;
      case 146: 
        break;
      case 147: 
        break;
      case 148: 
        break;
      case 149: 
        break;
      case 150: 
        break;
      case 151: 
        break;
      case 152: 
        break;
      case 153: 
        break;
      case 154: 
        break;
      case 155: 
        break;
      case 156: 
        break;
      case 157: 
        break;
      case 158: 
        break;
      case 159: 
        break;
      case 160: 
        break;
      case 161: 
        break;
      case 162: 
        break;
      case 163: 
        break;
      case 164: 
        break;
      case 165: 
        break;
      case 166: 
        break;
      case 167: 
        break;
      case 168: 
        break;
      case 169: 
        break;
      case 170: 
        break;
      case 171: 
        break;
      case 172: 
        break;
      case 173: 
        break;
      case 174: 
        break;
      case 175: 
        break;
      case 176: 
        break;
      case 177: 
        break;
      case 178: 
        break;
      case 179: 
        return 40;
      case 180: 
        return 41;
      case 181: 
        break;
      case 182: 
        break;
      
      case 183: 
        return 109;
      case 184: 
        return 110;
      case 185: 
        return 111;
      case 186: 
        return 112;
      case 187: 
        return 113;
      case 188: 
        return 114;
      case 189: 
        return 115;
      case 190: 
        return 116;
      case 191: 
        return 117;
      case 192: 
        return 118;
      case 193: 
        return 119;
      case 194: 
        return 120;
      case 200: 
        break;
      case 201: 
        break;
      case 202: 
        break;
      case 203: 
        break;
      case 204: 
        break;
      case 205: 
        break;
      case 206: 
        break;
      case 207: 
        break;
      case 208: 
        break;
      
      case 210: 
        return 5;
      case 211: 
        break;
      case 212: 
        break;
      case 213: 
        break;
      case 214: 
        break;
      case 215: 
        break;
      case 216: 
        break;
      case 217: 
        break;
      case 218: 
        break;
      case 219: 
        break;
      case 220: 
        break;
      case 221: 
        break;
      case 222: 
        break;
      case 223: 
        break;
      case 224: 
        break;
      case 225: 
        break;
      case 226: 
        break;
      case 227: 
        break;
      case 228: 
        break;
      case 229: 
        break;
      case 230: 
        break;
      case 231: 
        break;
      case 232: 
        break;
      case 233: 
        break;
      case 234: 
        break;
      case 235: 
        break;
      case 236: 
        break;
      case 237: 
        break;
      case 238: 
        break;
      case 239: 
        break;
      case 240: 
        return 0;
      case 241: 
        break;
      case 242: 
        break;
      case 243: 
        break;
      case 244: 
        break;
      case 245: 
        break;
      case 246: 
        break;
      case 247: 
        break;
      case 248: 
        break;
      }
      
      

      if (Window.DEBUG_KEY_EVENT) {
        System.out.println("TODO LinuxEVKey2NewtVKey: Unmapped EVKey " + paramShort);
      }
      
      return 0;
    }
  }
}
